Metadata-Version: 2.1
Name: BASFAPI
Version: 0.0.1
Summary: APIs for the future
Home-page: https://github.com/pypa/sampleproject
Author: Pablo Ruiz
Author-email: pablo.ruiz@basf.com
License: UNKNOWN
Platform: UNKNOWN
Classifier: Programming Language :: Python :: 3
Classifier: License :: OSI Approved :: MIT License
Classifier: Operating System :: OS Independent
Requires-Python: >=3.6
